pydif/__init__.py
pydif/pydif.py
pydif/test_pydif.py
pydif/dual/__init__.py
pydif/dual/dual.py
pydif/dual/test_dual.py
pydif/elementary/__init__.py
pydif/elementary/elementary.py
pydif/elementary/test_elementary.py
pydif/optimize/__init__.py
pydif/optimize/optimize.py
pydif/optimize/test_optimize.py
pydif-0.1.0.dist-info/LICENSE.txt
pydif-0.1.0.dist-info/METADATA
pydif-0.1.0.dist-info/WHEEL
pydif-0.1.0.dist-info/top_level.txt
pydif-0.1.0.dist-info/RECORD
